serpentine/__init__.py
serpentine/benchmarks.py
serpentine/serpentine.py
serpentine/version.py
serpentine-0.1.3.dist-info/LICENSE
serpentine-0.1.3.dist-info/METADATA
serpentine-0.1.3.dist-info/WHEEL
serpentine-0.1.3.dist-info/entry_points.txt
serpentine-0.1.3.dist-info/top_level.txt
serpentine-0.1.3.dist-info/RECORD
