Metadata-Version: 2.1
Name: serpentine
Version: 0.1.3
Summary: Serpentine binning package for Hi-C contact maps
Home-page: https://github.com/koszullab/serpentine
Author: vittore.scolari@pasteur.fr
License: Artistic License 2.0
Platform: UNKNOWN
Classifier: Development Status :: 3 - Alpha
Classifier: Intended Audience :: Science/Research
Classifier: Intended Audience :: Science/Research
Classifier: License :: OSI Approved :: Artistic License
Classifier: Programming Language :: Python
Classifier: Programming Language :: Python :: 3
Classifier: Programming Language :: Python :: 3 :: Only
Classifier: Programming Language :: Python :: 3.4
Classifier: Programming Language :: Python :: 3.5
Classifier: Programming Language :: Python :: 3.6
Classifier: Programming Language :: Python :: 3.7
Classifier: Topic :: Scientific/Engineering
Classifier: Topic :: Scientific/Engineering :: Bio-Informatics
Classifier: Topic :: Scientific/Engineering :: Visualization
Classifier: Operating System :: Microsoft :: Windows
Classifier: Operating System :: POSIX
Classifier: Operating System :: Unix
Classifier: Operating System :: MacOS
Requires-Python: >=3.4
Requires-Dist: numpy
Requires-Dist: scipy
Requires-Dist: docopt
Requires-Dist: matplotlib
Requires-Dist: pandas
